waldur_openstack/__init__.py
waldur_openstack/openstack/__init__.py
waldur_openstack/openstack/admin.py
waldur_openstack/openstack/apps.py
waldur_openstack/openstack/backend.py
waldur_openstack/openstack/executors.py
waldur_openstack/openstack/extension.py
waldur_openstack/openstack/filters.py
waldur_openstack/openstack/handlers.py
waldur_openstack/openstack/log.py
waldur_openstack/openstack/models.py
waldur_openstack/openstack/quotas.py
waldur_openstack/openstack/serializers.py
waldur_openstack/openstack/tasks.py
waldur_openstack/openstack/urls.py
waldur_openstack/openstack/views.py
waldur_openstack/openstack/management/__init__.py
waldur_openstack/openstack/management/commands/__init__.py
waldur_openstack/openstack/management/commands/initsecuritygroups.py
waldur_openstack/openstack/migrations/0001_initial.py
waldur_openstack/openstack/migrations/0002_volume.py
waldur_openstack/openstack/migrations/0003_snapshot.py
waldur_openstack/openstack/migrations/0004_dr_and_volume_backups.py
waldur_openstack/openstack/migrations/0005_ipmapping.py
waldur_openstack/openstack/migrations/0006_backups_restorations.py
waldur_openstack/openstack/migrations/0007_add_instance_tenant.py
waldur_openstack/openstack/migrations/0008_require_instance_tenant.py
waldur_openstack/openstack/migrations/0009_add_security_group_tenant.py
waldur_openstack/openstack/migrations/0010_require_security_group_tenant.py
waldur_openstack/openstack/migrations/0011_add_floating_ip_tenant.py
waldur_openstack/openstack/migrations/0012_require_floating_ip_tenant.py
waldur_openstack/openstack/migrations/0013_add_dr_backups_to_schedule.py
waldur_openstack/openstack/migrations/0014_instance_volumes.py
waldur_openstack/openstack/migrations/0015_instance_runtime_state.py
waldur_openstack/openstack/migrations/0016_backup_state.py
waldur_openstack/openstack/migrations/0017_backup_snapshots_and_restorations.py
waldur_openstack/openstack/migrations/0018_replace_security_group.py
waldur_openstack-0.43.4.dist-info/METADATA
waldur_openstack-0.43.4.dist-info/RECORD
waldur_openstack-0.43.4.dist-info/WHEEL
waldur_openstack-0.43.4.dist-info/entry_points.txt
waldur_openstack-0.43.4.dist-info/top_level.txt
