Metadata-Version: 2.1
Name: waldur-openstack
Version: 0.43.4
Summary: Waldur plugin for managing OpenStack resources.
Home-page: http://waldur.com
Author: OpenNode Team
Author-email: info@opennodecloud.com
License: MIT
Platform: UNKNOWN
Classifier: Framework :: Django
Classifier: Intended Audience :: Developers
Classifier: Intended Audience :: System Administrators
Classifier: Operating System :: OS Independent
Classifier: License :: OSI Approved :: MIT License
Provides-Extra: tests
Provides-Extra: dev
Requires-Dist: pbr (!=2.1.0)
Requires-Dist: Babel (!=2.4.0,>=2.3.4)
Requires-Dist: cmd2 (<0.9.0)
Requires-Dist: iptools (>=0.6.1)
Requires-Dist: waldur-core (>=0.161.1)
Requires-Dist: python-ceilometerclient (>=2.9.0)
Requires-Dist: python-cinderclient (>=3.1.0)
Requires-Dist: python-glanceclient (>=2.8.0)
Requires-Dist: python-keystoneclient (>=3.13.0)
Requires-Dist: python-neutronclient (>=6.5.0)
Requires-Dist: python-novaclient (>=9.1.0)
Provides-Extra: dev
Requires-Dist: Sphinx (==1.2.2); extra == 'dev'
Provides-Extra: tests
Requires-Dist: ddt (>=1.0.0); extra == 'tests'
